ykbio/__init__.py
ykbio/__pycache__/__init__.cpython-38.pyc
ykbio/io/__init__.py
ykbio/io/read.py
ykbio/io/write.py
ykbio/io/__pycache__/__init__.cpython-38.pyc
ykbio/io/__pycache__/read.cpython-38.pyc
ykbio/message/__init__.py
ykbio/message/exception.py
ykbio/message/__pycache__/__init__.cpython-38.pyc
ykbio/message/__pycache__/exception.cpython-38.pyc
ykbio/plot/__init__.py
ykbio/region/__init__.py
ykbio/region/extract.py
ykbio/region/filter.py
ykbio/region/intersect.py
ykbio/region/rmdup.py
ykbio/region/subtract.py
ykbio/stats/__init__.py
ykbio/utility/__init__.py
ykbbb-1.0.0.dist-info/LICENSE
ykbbb-1.0.0.dist-info/METADATA
ykbbb-1.0.0.dist-info/WHEEL
ykbbb-1.0.0.dist-info/top_level.txt
ykbbb-1.0.0.dist-info/RECORD
